alibabacloud_gateway_sls/__init__.py
alibabacloud_gateway_sls/client.py
alibabacloud_gateway_sls-0.4.0.dist-info/METADATA
alibabacloud_gateway_sls-0.4.0.dist-info/WHEEL
alibabacloud_gateway_sls-0.4.0.dist-info/top_level.txt
alibabacloud_gateway_sls-0.4.0.dist-info/RECORD
